hscifsspecutil.py
hscifsspecutil-0.1.2.dist-info/METADATA
hscifsspecutil-0.1.2.dist-info/WHEEL
hscifsspecutil-0.1.2.dist-info/RECORD
