Metadata-Version: 2.1
Name: hscifsspecutil
Version: 0.1.2
Summary: FsSpec and S3FS utilities
License: MIT
Author: Eetu Mäkelä
Author-email: eetu.makela@helsinki.fi
Requires-Python: >=3.10,<4
Classifier: License :: OSI Approved :: MIT License
Classifier: Programming Language :: Python :: 3
Classifier: Programming Language :: Python :: 3.10
Classifier: Programming Language :: Python :: 3.11
Classifier: Programming Language :: Python :: 3.12
Requires-Dist: fsspec (>=2024.9.0,<2025.0.0)
Requires-Dist: morefs[asynclocalfs] (>=0.2.2,<0.3.0)
Requires-Dist: multiprocessing-utils (>=0.4,<0.5)
Requires-Dist: pyyaml (>=6.0.2,<7.0.0)
Requires-Dist: s3fs (>=2024.9.0,<2025.0.0)
Requires-Dist: tqdm (>=4.66.5,<5.0.0)
